HIV_Isoform_Checker/HIV_Isoform_Checker.py
HIV_Isoform_Checker/Reference_aligner.py
HIV_Isoform_Checker/__init__.py
HIV_Isoform_Checker/__main__.py
HIV_Isoform_Checker-1.1.9.dist-info/LICENSE.txt
HIV_Isoform_Checker-1.1.9.dist-info/METADATA
HIV_Isoform_Checker-1.1.9.dist-info/WHEEL
HIV_Isoform_Checker-1.1.9.dist-info/entry_points.txt
HIV_Isoform_Checker-1.1.9.dist-info/top_level.txt
HIV_Isoform_Checker-1.1.9.dist-info/RECORD
