Metadata-Version: 2.1
Name: HIV_Isoform_Checker
Version: 1.1.9
Summary: Filters .gtf file of suspected HIV isoforms and confirms the isoform identities
Home-page: https://github.com/JessicaA2019/HIV_Isoform_Checker
Author: Jessica Lauren ALbert
Author-email: Jessica Lauren Albert <jessica.albert2001@gmail.com>
License: MIT License
Project-URL: Homepage, https://github.com/JessicaA2019/HIV_Isoform_Checker
Keywords: HIV,Isoforms,splicing,ONT sequencing
Classifier: Programming Language :: Python :: 3
Classifier: License :: OSI Approved :: MIT License
Classifier: Operating System :: OS Independent
Requires-Python: >=3
License-File: LICENSE.txt
